wyliozero/__init__.py
wyliozero/main.py
wyliozero/wfactory.py
wyliozero/winclude.py
wyliozero/wlcd.py
wyliozero-0.0.29.dist-info/LICENSE
wyliozero-0.0.29.dist-info/METADATA
wyliozero-0.0.29.dist-info/WHEEL
wyliozero-0.0.29.dist-info/top_level.txt
wyliozero-0.0.29.dist-info/RECORD
